tfunct/__init__.py
tfunct/__main__.py
tfunct/data/__init__.py
tfunct/data/example/.DS_Store
tfunct/data/example/ndvi.parquet
tfunct/data/example/pheno.parquet
tfunct/data/example/weather.parquet
tfunct/model/__init__.py
tfunct/model/gpp.py
tfunct/model/gyield.py
tfunct/model/ipar.py
tfunct/model/metrics.py
tfunct/model/prft.py
tfunct/model/sfvpd.py
tfunct/model/tday.py
tfunct/model/tpf.py
tfunct/util/__init__.py
tfunct/util/figures.py
tfunct-1.0.3.dev0.dist-info/LICENSE
tfunct-1.0.3.dev0.dist-info/METADATA
tfunct-1.0.3.dev0.dist-info/WHEEL
tfunct-1.0.3.dev0.dist-info/top_level.txt
tfunct-1.0.3.dev0.dist-info/RECORD
