Metadata-Version: 2.1
Name: tfunct
Version: 1.0.3.dev0
Summary: Library for estimating grain yield using temperature response functions
Home-page: https://github.com/egiron/TemperatureFunct
Author: Ernesto Giron Echeverry
Author-email: e.giron.e@gmail.com
Keywords: PRFT,WEFT,TPF,VPD,wheat,iPAR,photoperiod,RUE,NDVI,crop modeling
Classifier: Programming Language :: Python :: 3
Classifier: License :: Free for non-commercial use
Classifier: License :: OSI Approved :: GNU General Public License v3 or later (GPLv3+)
Classifier: Operating System :: OS Independent
Classifier: License :: Free for non-commercial use
Classifier: Environment :: Console
Classifier: Framework :: Jupyter
Classifier: Intended Audience :: Developers
Classifier: Intended Audience :: Education
Classifier: Intended Audience :: End Users/Desktop
Classifier: Intended Audience :: Information Technology
Classifier: Intended Audience :: Science/Research
License-File: LICENSE
Requires-Dist: numpy >=1.22.4
Requires-Dist: numba >=0.51.2
Requires-Dist: pandas >=1.5.3
Requires-Dist: scikit-learn >=1.2.2
Requires-Dist: scipy >=1.10.1
Requires-Dist: tqdm >=4.64.0
Requires-Dist: seaborn >=0.11.0
Requires-Dist: Shapely >=1.7.1
Requires-Dist: ipython >=7.21.0
Requires-Dist: duckdb >=0.8.1
Requires-Dist: pyarrow
Requires-Dist: click
